{
	"targets": ["민방위대 편입 1~2년차 대원"],
	"schedules": [
		{
			"TEL_NO": "055-330-3203",
			"ED_YMD": "20250407",
			"EDU_ST_TM": "1400",
			"EDU_END_TM": "1800",
			"EDU_PLC_RDN_ADDR": "경상남도 김해시 가야로 245 (구산동)",
			"EDU_PLC_BOTTOM": "민방위재난안전체험장(김해운동장 내)",
			"CVD_EDU_SE_NM": "기본교육",
			"EDU_TGT_SE_NM": "민방위대 편입 1~2년차 대원"
		},
		{
			"TEL_NO": "055-330-3203",
			"ED_YMD": "20250408",
			"EDU_ST_TM": "1400",
			"EDU_END_TM": "1800",
			"EDU_PLC_RDN_ADDR": "경상남도 김해시 가야로 245 (구산동)",
			"EDU_PLC_BOTTOM": "민방위재난안전체험장(김해운동장 내)",
			"CVD_EDU_SE_NM": "기본교육",
			"EDU_TGT_SE_NM": "민방위대 편입 1~2년차 대원"
		},
		{
			"TEL_NO": "055-330-3203",
			"ED_YMD": "20250409",
			"EDU_ST_TM": "1400",
			"EDU_END_TM": "1800",
			"EDU_PLC_RDN_ADDR": "경상남도 김해시 가야로 245 (구산동)",
			"EDU_PLC_BOTTOM": "민방위재난안전체험장(김해운동장 내)",
			"CVD_EDU_SE_NM": "기본교육",
			"EDU_TGT_SE_NM": "민방위대 편입 1~2년차 대원"
		},
		{
			"TEL_NO": "055-330-3203",
			"ED_YMD": "20250410",
			"EDU_ST_TM": "1400",
			"EDU_END_TM": "1800",
			"EDU_PLC_RDN_ADDR": "경상남도 김해시 가야로 245 (구산동)",
			"EDU_PLC_BOTTOM": "민방위재난안전체험장(김해운동장 내)",
			"CVD_EDU_SE_NM": "기본교육",
			"EDU_TGT_SE_NM": "민방위대 편입 1~2년차 대원"
		},
		{
			"TEL_NO": "055-330-3203",
			"ED_YMD": "20250411",
			"EDU_ST_TM": "1400",
			"EDU_END_TM": "1800",
			"EDU_PLC_RDN_ADDR": "경상남도 김해시 가야로 245 (구산동)",
			"EDU_PLC_BOTTOM": "민방위재난안전체험장(김해운동장 내)",
			"CVD_EDU_SE_NM": "기본교육",
			"EDU_TGT_SE_NM": "민방위대 편입 1~2년차 대원"
		},
		{
			"TEL_NO": "055-330-3203",
			"ED_YMD": "20250414",
			"EDU_ST_TM": "1400",
			"EDU_END_TM": "1800",
			"EDU_PLC_RDN_ADDR": "경상남도 김해시 가야로 245 (구산동)",
			"EDU_PLC_BOTTOM": "민방위재난안전체험장(김해운동장 내)",
			"CVD_EDU_SE_NM": "기본교육",
			"EDU_TGT_SE_NM": "민방위대 편입 1~2년차 대원"
		},
		{
			"TEL_NO": "055-330-3203",
			"ED_YMD": "20250415",
			"EDU_ST_TM": "1400",
			"EDU_END_TM": "1800",
			"EDU_PLC_RDN_ADDR": "경상남도 김해시 가야로 245 (구산동)",
			"EDU_PLC_BOTTOM": "민방위재난안전체험장(김해운동장 내)",
			"CVD_EDU_SE_NM": "기본교육",
			"EDU_TGT_SE_NM": "민방위대 편입 1~2년차 대원"
		},
		{
			"TEL_NO": "055-330-3203",
			"ED_YMD": "20250416",
			"EDU_ST_TM": "1400",
			"EDU_END_TM": "1800",
			"EDU_PLC_RDN_ADDR": "경상남도 김해시 가야로 245 (구산동)",
			"EDU_PLC_BOTTOM": "민방위재난안전체험장(김해운동장 내)",
			"CVD_EDU_SE_NM": "기본교육",
			"EDU_TGT_SE_NM": "민방위대 편입 1~2년차 대원"
		},
		{
			"TEL_NO": "055-330-3203",
			"ED_YMD": "20250417",
			"EDU_ST_TM": "1400",
			"EDU_END_TM": "1800",
			"EDU_PLC_RDN_ADDR": "경상남도 김해시 가야로 245 (구산동)",
			"EDU_PLC_BOTTOM": "민방위재난안전체험장(김해운동장 내)",
			"CVD_EDU_SE_NM": "기본교육",
			"EDU_TGT_SE_NM": "민방위대 편입 1~2년차 대원"
		},
		{
			"TEL_NO": "055-330-3203",
			"ED_YMD": "20250418",
			"EDU_ST_TM": "1400",
			"EDU_END_TM": "1800",
			"EDU_PLC_RDN_ADDR": "경상남도 김해시 가야로 245 (구산동)",
			"EDU_PLC_BOTTOM": "민방위재난안전체험장(김해운동장 내)",
			"CVD_EDU_SE_NM": "기본교육",
			"EDU_TGT_SE_NM": "민방위대 편입 1~2년차 대원"
		},
		{
			"TEL_NO": "055-330-3203",
			"ED_YMD": "20250421",
			"EDU_ST_TM": "1400",
			"EDU_END_TM": "1800",
			"EDU_PLC_RDN_ADDR": "경상남도 김해시 가야로 245 (구산동)",
			"EDU_PLC_BOTTOM": "민방위재난안전체험장(김해운동장 내)",
			"CVD_EDU_SE_NM": "기본교육",
			"EDU_TGT_SE_NM": "민방위대 편입 1~2년차 대원"
		},
		{
			"TEL_NO": "055-330-3203",
			"ED_YMD": "20250422",
			"EDU_ST_TM": "1400",
			"EDU_END_TM": "1800",
			"EDU_PLC_RDN_ADDR": "경상남도 김해시 가야로 245 (구산동)",
			"EDU_PLC_BOTTOM": "민방위재난안전체험장(김해운동장 내)",
			"CVD_EDU_SE_NM": "기본교육",
			"EDU_TGT_SE_NM": "민방위대 편입 1~2년차 대원"
		},
		{
			"TEL_NO": "055-330-3203",
			"ED_YMD": "20250423",
			"EDU_ST_TM": "1400",
			"EDU_END_TM": "1800",
			"EDU_PLC_RDN_ADDR": "경상남도 김해시 가야로 245 (구산동)",
			"EDU_PLC_BOTTOM": "민방위재난안전체험장(김해운동장 내)",
			"CVD_EDU_SE_NM": "기본교육",
			"EDU_TGT_SE_NM": "민방위대 편입 1~2년차 대원"
		},
		{
			"TEL_NO": "055-330-3203",
			"ED_YMD": "20250424",
			"EDU_ST_TM": "1400",
			"EDU_END_TM": "1800",
			"EDU_PLC_RDN_ADDR": "경상남도 김해시 가야로 245 (구산동)",
			"EDU_PLC_BOTTOM": "민방위재난안전체험장(김해운동장 내)",
			"CVD_EDU_SE_NM": "기본교육",
			"EDU_TGT_SE_NM": "민방위대 편입 1~2년차 대원"
		},
		{
			"TEL_NO": "055-330-3203",
			"ED_YMD": "20250425",
			"EDU_ST_TM": "1400",
			"EDU_END_TM": "1800",
			"EDU_PLC_RDN_ADDR": "경상남도 김해시 가야로 245 (구산동)",
			"EDU_PLC_BOTTOM": "민방위재난안전체험장(김해운동장 내)",
			"CVD_EDU_SE_NM": "기본교육",
			"EDU_TGT_SE_NM": "민방위대 편입 1~2년차 대원"
		},
		{
			"TEL_NO": "055-330-3203",
			"ED_YMD": "20250428",
			"EDU_ST_TM": "1400",
			"EDU_END_TM": "1800",
			"EDU_PLC_RDN_ADDR": "경상남도 김해시 가야로 245 (구산동)",
			"EDU_PLC_BOTTOM": "민방위재난안전체험장(김해운동장 내)",
			"CVD_EDU_SE_NM": "기본교육",
			"EDU_TGT_SE_NM": "민방위대 편입 1~2년차 대원"
		},
		{
			"TEL_NO": "055-330-3203",
			"ED_YMD": "20250429",
			"EDU_ST_TM": "1400",
			"EDU_END_TM": "1800",
			"EDU_PLC_RDN_ADDR": "경상남도 김해시 가야로 245 (구산동)",
			"EDU_PLC_BOTTOM": "민방위재난안전체험장(김해운동장 내)",
			"CVD_EDU_SE_NM": "기본교육",
			"EDU_TGT_SE_NM": "민방위대 편입 1~2년차 대원"
		},
		{
			"TEL_NO": "055-330-3203",
			"ED_YMD": "20250430",
			"EDU_ST_TM": "1400",
			"EDU_END_TM": "1800",
			"EDU_PLC_RDN_ADDR": "경상남도 김해시 가야로 245 (구산동)",
			"EDU_PLC_BOTTOM": "민방위재난안전체험장(김해운동장 내)",
			"CVD_EDU_SE_NM": "기본교육",
			"EDU_TGT_SE_NM": "민방위대 편입 1~2년차 대원"
		}
	],
	"regionText": "경상남도 김해시"
}
