{
	"targets": [
		"신편대원",
		"민방위대 편입 1~2년차 대원",
		"민방위대 편입 2년차 대원",
		"민방위대 편입 3~4년차 대원",
		"민방위대 편입 5년차 이상",
		"민방위대장"
	],
	"schedules": [
		{
			"TEL_NO": "063-454-3833",
			"ED_YMD": "20230406",
			"EDU_ST_TM": "0000",
			"EDU_END_TM": "2359",
			"EDU_PLC_BOTTOM": "민방위 사이버 교육센터(https://kcmes.or.kr/)",
			"CVD_EDU_SE_NM": "사이버교육",
			"EDU_TGT_SE_NM": "민방위대 편입 3~4년차 대원",
			"EDU_LOCAL_ID": "6450000-4670000-0"
		},
		{
			"TEL_NO": "063-454-3833",
			"ED_YMD": "20230406",
			"EDU_ST_TM": "0000",
			"EDU_END_TM": "2359",
			"EDU_PLC_BOTTOM": "민방위 사이버 교육센터(https://kcmes.or.kr/)",
			"CVD_EDU_SE_NM": "사이버교육",
			"EDU_TGT_SE_NM": "민방위대 편입 5년차 이상",
			"EDU_LOCAL_ID": "6450000-4670000-1"
		},
		{
			"TEL_NO": "063-454-3833",
			"ED_YMD": "20230411",
			"EDU_ST_TM": "1300",
			"EDU_END_TM": "1700",
			"EDU_PLC_RDN_ADDR": "전라북도 군산시 청소년회관로 75, 청소년수련관 (송풍동)",
			"EDU_PLC_BOTTOM": "청소년수련관",
			"CVD_EDU_SE_NM": "기본교육",
			"EDU_TGT_SE_NM": "민방위대 편입 1~2년차 대원",
			"EDU_LOCAL_ID": "6450000-4670000-2"
		},
		{
			"TEL_NO": "063-454-3833",
			"ED_YMD": "20230411",
			"EDU_ST_TM": "0900",
			"EDU_END_TM": "1800",
			"EDU_PLC_RDN_ADDR": "전라북도 군산시 내항2길 125, 옥도면사무소 (금동)",
			"EDU_PLC_BOTTOM": "옥도면사무소 지정장소",
			"CVD_EDU_SE_NM": "서면교육",
			"EDU_TGT_SE_NM": "민방위대 편입 1~2년차 대원",
			"EDU_LOCAL_ID": "6450000-4670000-3"
		},
		{
			"TEL_NO": "063-454-3833",
			"ED_YMD": "20230411",
			"EDU_ST_TM": "0900",
			"EDU_END_TM": "1800",
			"EDU_PLC_RDN_ADDR": "전라북도 군산시 내항2길 125, 옥도면사무소 (금동)",
			"EDU_PLC_BOTTOM": "옥도면사무소 지정장소",
			"CVD_EDU_SE_NM": "서면교육",
			"EDU_TGT_SE_NM": "민방위대장",
			"EDU_LOCAL_ID": "6450000-4670000-4"
		},
		{
			"TEL_NO": "063-454-3833",
			"ED_YMD": "20230412",
			"EDU_ST_TM": "1300",
			"EDU_END_TM": "1700",
			"EDU_PLC_RDN_ADDR": "전라북도 군산시 청소년회관로 75, 청소년수련관 (송풍동)",
			"EDU_PLC_BOTTOM": "청소년수련관",
			"CVD_EDU_SE_NM": "기본교육",
			"EDU_TGT_SE_NM": "민방위대 편입 1~2년차 대원",
			"EDU_LOCAL_ID": "6450000-4670000-5"
		},
		{
			"TEL_NO": "063-454-3833",
			"ED_YMD": "20230414",
			"EDU_ST_TM": "1300",
			"EDU_END_TM": "1700",
			"EDU_PLC_RDN_ADDR": "전라북도 군산시 청소년회관로 75, 청소년수련관 (송풍동)",
			"EDU_PLC_BOTTOM": "청소년수련관",
			"CVD_EDU_SE_NM": "기본교육",
			"EDU_TGT_SE_NM": "민방위대 편입 1~2년차 대원",
			"EDU_LOCAL_ID": "6450000-4670000-6"
		},
		{
			"TEL_NO": "063-454-3833",
			"ED_YMD": "20230414",
			"EDU_ST_TM": "1300",
			"EDU_END_TM": "1700",
			"EDU_PLC_RDN_ADDR": "전라북도 군산시 청소년회관로 75, 청소년수련관 (송풍동)",
			"EDU_PLC_BOTTOM": "청소년수련관",
			"CVD_EDU_SE_NM": "기본교육",
			"EDU_TGT_SE_NM": "신편대원",
			"EDU_LOCAL_ID": "6450000-4670000-7"
		},
		{
			"TEL_NO": "063-454-3833",
			"ED_YMD": "20230418",
			"EDU_ST_TM": "1300",
			"EDU_END_TM": "1700",
			"EDU_PLC_RDN_ADDR": "전라북도 군산시 청소년회관로 75, 청소년수련관 (송풍동)",
			"EDU_PLC_BOTTOM": "청소년수련관",
			"CVD_EDU_SE_NM": "기본교육",
			"EDU_TGT_SE_NM": "민방위대 편입 1~2년차 대원",
			"EDU_LOCAL_ID": "6450000-4670000-8"
		},
		{
			"TEL_NO": "063-454-3833",
			"ED_YMD": "20230418",
			"EDU_ST_TM": "1300",
			"EDU_END_TM": "1700",
			"EDU_PLC_RDN_ADDR": "전라북도 군산시 청소년회관로 75, 청소년수련관 (송풍동)",
			"EDU_PLC_BOTTOM": "청소년수련관",
			"CVD_EDU_SE_NM": "기본교육",
			"EDU_TGT_SE_NM": "민방위대 편입 2년차 대원",
			"EDU_LOCAL_ID": "6450000-4670000-9"
		},
		{
			"TEL_NO": "063-454-3833",
			"ED_YMD": "20230419",
			"EDU_ST_TM": "1300",
			"EDU_END_TM": "1700",
			"EDU_PLC_RDN_ADDR": "전라북도 군산시 청소년회관로 75, 청소년수련관 (송풍동)",
			"EDU_PLC_BOTTOM": "청소년수련관",
			"CVD_EDU_SE_NM": "기본교육",
			"EDU_TGT_SE_NM": "민방위대 편입 1~2년차 대원",
			"EDU_LOCAL_ID": "6450000-4670000-10"
		},
		{
			"TEL_NO": "063-454-3833",
			"ED_YMD": "20230420",
			"EDU_ST_TM": "1300",
			"EDU_END_TM": "1700",
			"EDU_PLC_RDN_ADDR": "전라북도 군산시 청소년회관로 75, 청소년수련관 (송풍동)",
			"EDU_PLC_BOTTOM": "청소년수련관",
			"CVD_EDU_SE_NM": "기본교육",
			"EDU_TGT_SE_NM": "민방위대 편입 1~2년차 대원",
			"EDU_LOCAL_ID": "6450000-4670000-11"
		},
		{
			"TEL_NO": "063-454-3833",
			"ED_YMD": "20230421",
			"EDU_ST_TM": "1300",
			"EDU_END_TM": "1700",
			"EDU_PLC_RDN_ADDR": "전라북도 군산시 청소년회관로 75, 청소년수련관 (송풍동)",
			"EDU_PLC_BOTTOM": "청소년수련관",
			"CVD_EDU_SE_NM": "기본교육",
			"EDU_TGT_SE_NM": "민방위대 편입 1~2년차 대원",
			"EDU_LOCAL_ID": "6450000-4670000-12"
		}
	],
	"regionText": "전라북도 군산시"
}
